{"cameraMode":{"drawMode":0,"name":"Shaded","section":"Shading Mode"},"sceneLighting":true,"audioPlay":false,"sceneViewState":{"showFog":true,"showMaterialUpdate":false,"showSkybox":true,"showFlares":true,"showImageEffects":true,"showParticleSystems":true},"in2DMode":false,"pivot":{"x":7.747430801391602,"y":4.3668317794799809,"z":4.242645740509033},"rotation":{"x":0.075336754322052,"y":0.8900244832038879,"z":-0.1594841480255127,"w":0.42042210698127749},"size":21.15067481994629,"orthographic":false}